pyauto_desktop/__init__.py
pyauto_desktop/capture_tool.py
pyauto_desktop/detection.py
pyauto_desktop/dpi_manager.py
pyauto_desktop/editor.py
pyauto_desktop/functions.py
pyauto_desktop/main.py
pyauto_desktop/overlay.py
pyauto_desktop/style.py
pyauto_desktop/text_recognition.py
pyauto_desktop/ui_setup.py
pyauto_desktop/utils.py
pyauto_desktop/widgets.py
pyauto_desktop/window_control.py
pyauto_desktop-0.4.1.dist-info/licenses/LICENSE
pyauto_desktop-0.4.1.dist-info/METADATA
pyauto_desktop-0.4.1.dist-info/WHEEL
pyauto_desktop-0.4.1.dist-info/top_level.txt
pyauto_desktop-0.4.1.dist-info/RECORD
