Metadata-Version: 2.4
Name: pyauto-desktop
Version: 0.4.1
Summary: A desktop automation tool for image recognition.
Home-page: https://github.com/Omar-F-Rashed/pyauto-desktop
Author: Omar Rashed
Author-email: justdev.contact@gmail.com
Classifier: Programming Language :: Python :: 3
Classifier: Operating System :: OS Independent
Requires-Python: >=3.6
License-File: LICENSE
Requires-Dist: opencv-python
Requires-Dist: numpy
Requires-Dist: Pillow
Requires-Dist: PyQt6
Requires-Dist: pynput
Requires-Dist: mss
Requires-Dist: pydirectinput
Requires-Dist: pywinctl
Requires-Dist: rapidocr
Requires-Dist: onnxruntime
Dynamic: author
Dynamic: author-email
Dynamic: classifier
Dynamic: description
Dynamic: description-content-type
Dynamic: home-page
Dynamic: license-file
Dynamic: requires-dist
Dynamic: requires-python
Dynamic: summary
